starcache/__init__.py
starcache/backends.py
starcache/cached_responses.py
starcache/middleware.py
starcache/py.typed
starcache/serializers.py
starcache/utils.py
starcache/vary.py
starcache-0.1.1.dist-info/WHEEL
starcache-0.1.1.dist-info/METADATA
starcache-0.1.1.dist-info/RECORD
