Metadata-Version: 2.3
Name: starcache
Version: 0.1.1
Summary: A modern HTTP caching library for Starlette and FastAPI.
Author: Matthew Messinger
Author-email: Matthew Messinger <mattmess1221@gmail.com>
Classifier: Development Status :: 4 - Beta
Classifier: Framework :: AsyncIO
Classifier: Framework :: FastAPI
Classifier: License :: OSI Approved :: MIT License
Classifier: Programming Language :: Python :: 3.10
Classifier: Programming Language :: Python :: 3.11
Classifier: Programming Language :: Python :: 3.12
Classifier: Programming Language :: Python :: 3.13
Classifier: Programming Language :: Python :: 3.14
Classifier: Topic :: Software Development :: Libraries
Classifier: Typing :: Typed
Requires-Dist: starlette>=0.50.0
Requires-Dist: typing-extensions>=4.15.0 ; python_full_version < '3.12'
Requires-Python: >=3.10
